pyensemblrest/__init__.py
pyensemblrest/ensembl_config.py
pyensemblrest/ensemblrest.py
pyensemblrest/exceptions.py
pyensemblrest-0.3.3.dist-info/METADATA
pyensemblrest-0.3.3.dist-info/WHEEL
pyensemblrest-0.3.3.dist-info/licenses/LICENSE.md
pyensemblrest-0.3.3.dist-info/RECORD
