Metadata-Version: 2.4
Name: pyEnsemblRest
Version: 0.3.3
Summary: A Python Ensembl REST API client
License: GPL-3.0-or-later
License-File: LICENSE.md
Keywords: ensembl,python,rest,api
Author: Steve Moss
Author-email: gawbul@gmail.com
Maintainer: Steve Moss
Maintainer-email: gawbul@gmail.com
Requires-Python: >=3.10,<3.14
Classifier: Development Status :: 4 - Beta
Classifier: Intended Audience :: Developers
Classifier: License :: OSI Approved :: GNU General Public License v3 (GPLv3)
Classifier: License :: OSI Approved :: GNU General Public License v3 or later (GPLv3+)
Classifier: Programming Language :: Python :: 3
Classifier: Programming Language :: Python :: 3.10
Classifier: Programming Language :: Python :: 3.11
Classifier: Programming Language :: Python :: 3.12
Classifier: Programming Language :: Python :: 3.13
Classifier: Topic :: Scientific/Engineering :: Bio-Informatics
Classifier: Topic :: Software Development :: Libraries :: Python Modules
Requires-Dist: coveralls (>=4.0.2,<5.0.0)
Requires-Dist: mypy (>=1.18.0,<2.0.0)
Requires-Dist: pre-commit (>=4.4.0,<5.0.0)
Requires-Dist: requests (>=2.32.5,<3.0.0)
Requires-Dist: ruff (>=0.14.0,<0.15.0)
Requires-Dist: types-requests (>=2.32.4.20250913,<3.0.0.0)
Project-URL: Documentation, https://github.com/gawbul/pyEnsemblRest?tab=readme-ov-file
Project-URL: Homepage, https://github.com/gawbul/pyEnsemblRest
Project-URL: Repository, https://github.com/gawbul/pyEnsemblRest
